[
    {
        "bbox": [
            528,
            106,
            534,
            127
        ],
        "class": 0,
        "iou": 0
    },
    {
        "bbox": [
            437,
            241,
            461,
            279
        ],
        "class": 0,
        "iou": 0
    },
    {
        "bbox": [
            12,
            112,
            34,
            124
        ],
        "class": 0,
        "iou": 0
    },
    {
        "bbox": [
            382,
            233,
            447,
            283
        ],
        "class": 0,
        "iou": 0
    },
    {
        "bbox": [
            243,
            243,
            265,
            259
        ],
        "class": 0,
        "iou": 0.00909560723514212
    },
    {
        "bbox": [
            312,
            283,
            326,
            300
        ],
        "class": 0,
        "iou": 0
    },
    {
        "bbox": [
            416,
            7,
            534,
            8
        ],
        "class": 0,
        "iou": 0
    },
    {
        "bbox": [
            327,
            7,
            411,
            15
        ],
        "class": 0,
        "iou": 0
    },
    {
        "bbox": [
            370,
            239,
            407,
            266
        ],
        "class": 0,
        "iou": 0
    },
    {
        "bbox": [
            345,
            246,
            411,
            300
        ],
        "class": 0,
        "iou": 0
    },
    {
        "bbox": [
            404,
            235,
            414,
            266
        ],
        "class": 0,
        "iou": 0
    },
    {
        "bbox": [
            417,
            234,
            442,
            272
        ],
        "class": 0,
        "iou": 0
    },
    {
        "bbox": [
            0,
            0,
            495,
            19
        ],
        "class": 0,
        "iou": 0
    },
    {
        "bbox": [
            437,
            242,
            461,
            279
        ],
        "class": 0,
        "iou": 0
    },
    {
        "bbox": [
            253,
            138,
            272,
            149
        ],
        "class": 0,
        "iou": 0.005400516795865633
    },
    {
        "bbox": [
            417,
            234,
            443,
            267
        ],
        "class": 0,
        "iou": 0
    },
    {
        "bbox": [
            0,
            109,
            534,
            300
        ],
        "class": null,
        "iou": 0.3794340843579034
    },
    {
        "bbox": [
            417,
            234,
            438,
            258
        ],
        "class": 0,
        "iou": 0
    },
    {
        "bbox": [
            293,
            204,
            310,
            228
        ],
        "class": 0,
        "iou": 0.004314329738058551
    },
    {
        "bbox": [
            124,
            138,
            163,
            159
        ],
        "class": 0,
        "iou": 0.02116279069767442
    },
    {
        "bbox": [
            53,
            270,
            91,
            286
        ],
        "class": 0,
        "iou": 0
    },
    {
        "bbox": [
            382,
            233,
            446,
            283
        ],
        "class": 0,
        "iou": 0
    },
    {
        "bbox": [
            129,
            13,
            192,
            16
        ],
        "class": 0,
        "iou": 0
    },
    {
        "bbox": [
            202,
            237,
            237,
            268
        ],
        "class": 0,
        "iou": 0.026180036110394635
    },
    {
        "bbox": [
            116,
            115,
            159,
            127
        ],
        "class": 0,
        "iou": 0.01220865704772475
    },
    {
        "bbox": [
            0,
            0,
            534,
            300
        ],
        "class": 0,
        "iou": 0.24157303370786518
    },
    {
        "bbox": [
            216,
            0,
            281,
            17
        ],
        "class": 0,
        "iou": 0
    },
    {
        "bbox": [
            285,
            221,
            311,
            257
        ],
        "class": 0,
        "iou": 0.013812154696132596
    },
    {
        "bbox": [
            418,
            235,
            442,
            267
        ],
        "class": 0,
        "iou": 0
    },
    {
        "bbox": [
            184,
            178,
            230,
            215
        ],
        "class": 0,
        "iou": 0.04397932816537468
    },
    {
        "bbox": [
            144,
            141,
            164,
            154
        ],
        "class": 0,
        "iou": 0.006718346253229974
    },
    {
        "bbox": [
            0,
            252,
            44,
            283
        ],
        "class": 0,
        "iou": 0.0006993705664901589
    },
    {
        "bbox": [
            512,
            32,
            534,
            79
        ],
        "class": 0,
        "iou": 0
    },
    {
        "bbox": [
            73,
            109,
            213,
            152
        ],
        "class": 0,
        "iou": 0.12701612903225806
    },
    {
        "bbox": [
            404,
            234,
            415,
            266
        ],
        "class": 0,
        "iou": 0
    },
    {
        "bbox": [
            294,
            198,
            315,
            221
        ],
        "class": 0,
        "iou": 0.003534383403764887
    },
    {
        "bbox": [
            202,
            211,
            310,
            270
        ],
        "class": 0,
        "iou": 0.1358298472859231
    },
    {
        "bbox": [
            0,
            115,
            301,
            300
        ],
        "class": 1,
        "iou": 0.694980694980695
    },
    {
        "bbox": [
            162,
            205,
            177,
            221
        ],
        "class": 0,
        "iou": 0.006201550387596899
    },
    {
        "bbox": [
            66,
            120,
            115,
            136
        ],
        "class": 0,
        "iou": 0.020258397932816537
    },
    {
        "bbox": [
            419,
            265,
            437,
            281
        ],
        "class": 0,
        "iou": 0
    },
    {
        "bbox": [
            208,
            96,
            224,
            112
        ],
        "class": 0,
        "iou": 0
    },
    {
        "bbox": [
            394,
            0,
            479,
            11
        ],
        "class": 0,
        "iou": 0
    },
    {
        "bbox": [
            320,
            64,
            352,
            96
        ],
        "class": 0,
        "iou": 0
    },
    {
        "bbox": [
            79,
            123,
            96,
            136
        ],
        "class": 0,
        "iou": 0.005710594315245478
    },
    {
        "bbox": [
            383,
            261,
            405,
            267
        ],
        "class": 0,
        "iou": 0
    },
    {
        "bbox": [
            165,
            253,
            198,
            262
        ],
        "class": 0,
        "iou": 0.007674418604651163
    },
    {
        "bbox": [
            119,
            238,
            159,
            261
        ],
        "class": 0,
        "iou": 0.023772609819121448
    },
    {
        "bbox": [
            104,
            271,
            234,
            300
        ],
        "class": 0,
        "iou": 0
    },
    {
        "bbox": [
            526,
            192,
            534,
            240
        ],
        "class": 0,
        "iou": 0
    },
    {
        "bbox": [
            0,
            111,
            34,
            144
        ],
        "class": 0,
        "iou": 0
    },
    {
        "bbox": [
            495,
            0,
            534,
            10
        ],
        "class": 0,
        "iou": 0
    },
    {
        "bbox": [
            119,
            234,
            238,
            268
        ],
        "class": 0,
        "iou": 0.09779649699522318
    },
    {
        "bbox": [
            47,
            183,
            73,
            205
        ],
        "class": 0,
        "iou": 0.014780361757105943
    },
    {
        "bbox": [
            425,
            240,
            433,
            261
        ],
        "class": 0,
        "iou": 0
    },
    {
        "bbox": [
            64,
            0,
            145,
            6
        ],
        "class": 0,
        "iou": 0
    },
    {
        "bbox": [
            0,
            14,
            96,
            19
        ],
        "class": 0,
        "iou": 0
    },
    {
        "bbox": [
            226,
            0,
            254,
            7
        ],
        "class": 0,
        "iou": 0
    },
    {
        "bbox": [
            381,
            232,
            415,
            266
        ],
        "class": 0,
        "iou": 0
    },
    {
        "bbox": [
            94,
            92,
            136,
            123
        ],
        "class": 0,
        "iou": 0.007404049561801148
    },
    {
        "bbox": [
            224,
            0,
            479,
            16
        ],
        "class": 0,
        "iou": 0
    },
    {
        "bbox": [
            120,
            246,
            157,
            259
        ],
        "class": 0,
        "iou": 0.012428940568475452
    },
    {
        "bbox": [
            431,
            240,
            443,
            266
        ],
        "class": 0,
        "iou": 0
    },
    {
        "bbox": [
            277,
            256,
            297,
            270
        ],
        "class": 0,
        "iou": 0.005157297576070139
    },
    {
        "bbox": [
            0,
            0,
            205,
            19
        ],
        "class": 0,
        "iou": 0
    },
    {
        "bbox": [
            254,
            137,
            272,
            153
        ],
        "class": 0,
        "iou": 0.0074418604651162795
    },
    {
        "bbox": [
            0,
            122,
            35,
            143
        ],
        "class": 0,
        "iou": 0
    },
    {
        "bbox": [
            64,
            0,
            127,
            6
        ],
        "class": 0,
        "iou": 0
    },
    {
        "bbox": [
            343,
            0,
            534,
            7
        ],
        "class": 0,
        "iou": 0
    },
    {
        "bbox": [
            383,
            261,
            411,
            281
        ],
        "class": 0,
        "iou": 0
    },
    {
        "bbox": [
            500,
            189,
            534,
            300
        ],
        "class": 0,
        "iou": 0
    },
    {
        "bbox": [
            48,
            183,
            73,
            204
        ],
        "class": 0,
        "iou": 0.013565891472868217
    },
    {
        "bbox": [
            119,
            234,
            161,
            261
        ],
        "class": 0,
        "iou": 0.02930232558139535
    },
    {
        "bbox": [
            507,
            254,
            529,
            276
        ],
        "class": 0,
        "iou": 0
    },
    {
        "bbox": [
            417,
            235,
            438,
            263
        ],
        "class": 0,
        "iou": 0
    },
    {
        "bbox": [
            0,
            14,
            160,
            33
        ],
        "class": 0,
        "iou": 0
    },
    {
        "bbox": [
            352,
            163,
            382,
            187
        ],
        "class": 0,
        "iou": 0
    },
    {
        "bbox": [
            0,
            118,
            511,
            300
        ],
        "class": null,
        "iou": 0.4083064222930345
    },
    {
        "bbox": [
            268,
            155,
            310,
            189
        ],
        "class": 0,
        "iou": 0.027868852459016394
    },
    {
        "bbox": [
            90,
            264,
            131,
            281
        ],
        "class": 0,
        "iou": 0.0020857179193691975
    },
    {
        "bbox": [
            199,
            270,
            234,
            293
        ],
        "class": 0,
        "iou": 0
    },
    {
        "bbox": [
            326,
            0,
            396,
            9
        ],
        "class": 0,
        "iou": 0
    },
    {
        "bbox": [
            0,
            0,
            197,
            19
        ],
        "class": 0,
        "iou": 0
    },
    {
        "bbox": [
            334,
            12,
            384,
            17
        ],
        "class": 0,
        "iou": 0
    },
    {
        "bbox": [
            244,
            138,
            275,
            153
        ],
        "class": 0,
        "iou": 0.012015503875968992
    },
    {
        "bbox": [
            319,
            57,
            353,
            97
        ],
        "class": 0,
        "iou": 0
    },
    {
        "bbox": [
            280,
            186,
            302,
            209
        ],
        "class": 0,
        "iou": 0.011872193258658958
    },
    {
        "bbox": [
            207,
            97,
            534,
            300
        ],
        "class": 0,
        "iou": 0.15307634065246734
    },
    {
        "bbox": [
            216,
            237,
            238,
            252
        ],
        "class": 0,
        "iou": 0.008527131782945736
    },
    {
        "bbox": [
            0,
            0,
            479,
            18
        ],
        "class": 0,
        "iou": 0
    },
    {
        "bbox": [
            364,
            163,
            382,
            175
        ],
        "class": 0,
        "iou": 0
    },
    {
        "bbox": [
            115,
            115,
            159,
            127
        ],
        "class": 0,
        "iou": 0.012492256865579187
    },
    {
        "bbox": [
            0,
            122,
            34,
            144
        ],
        "class": 0,
        "iou": 0
    },
    {
        "bbox": [
            157,
            112,
            264,
            149
        ],
        "class": 0,
        "iou": 0.09024228174197506
    },
    {
        "bbox": [
            416,
            233,
            441,
            267
        ],
        "class": 0,
        "iou": 0
    },
    {
        "bbox": [
            65,
            0,
            133,
            10
        ],
        "class": 0,
        "iou": 0
    },
    {
        "bbox": [
            521,
            16,
            534,
            32
        ],
        "class": 0,
        "iou": 0
    },
    {
        "bbox": [
            351,
            233,
            406,
            260
        ],
        "class": 0,
        "iou": 0
    },
    {
        "bbox": [
            144,
            115,
            215,
            160
        ],
        "class": 0,
        "iou": 0.08057568801423745
    },
    {
        "bbox": [
            336,
            5,
            496,
            24
        ],
        "class": 0,
        "iou": 0
    },
    {
        "bbox": [
            224,
            0,
            256,
            8
        ],
        "class": 0,
        "iou": 0
    },
    {
        "bbox": [
            235,
            114,
            282,
            128
        ],
        "class": 0,
        "iou": 0.01453833066969119
    },
    {
        "bbox": [
            504,
            192,
            534,
            300
        ],
        "class": 0,
        "iou": 0
    },
    {
        "bbox": [
            144,
            137,
            200,
            161
        ],
        "class": 0,
        "iou": 0.03472868217054263
    },
    {
        "bbox": [
            0,
            111,
            33,
            126
        ],
        "class": 0,
        "iou": 0
    },
    {
        "bbox": [
            465,
            0,
            519,
            3
        ],
        "class": 0,
        "iou": 0
    },
    {
        "bbox": [
            32,
            17,
            160,
            32
        ],
        "class": 0,
        "iou": 0
    },
    {
        "bbox": [
            5,
            272,
            45,
            281
        ],
        "class": 0,
        "iou": 0
    },
    {
        "bbox": [
            326,
            6,
            412,
            15
        ],
        "class": 0,
        "iou": 0
    },
    {
        "bbox": [
            176,
            7,
            208,
            14
        ],
        "class": 0,
        "iou": 0
    },
    {
        "bbox": [
            178,
            178,
            225,
            221
        ],
        "class": 0,
        "iou": 0.052222222222222225
    },
    {
        "bbox": [
            280,
            186,
            315,
            221
        ],
        "class": 0,
        "iou": 0.017845761631612493
    },
    {
        "bbox": [
            199,
            211,
            310,
            293
        ],
        "class": 0,
        "iou": 0.13148862641134282
    },
    {
        "bbox": [
            0,
            7,
            534,
            145
        ],
        "class": 0,
        "iou": 0.07131827280526165
    },
    {
        "bbox": [
            0,
            14,
            144,
            20
        ],
        "class": 0,
        "iou": 0
    },
    {
        "bbox": [
            129,
            8,
            209,
            17
        ],
        "class": 0,
        "iou": 0
    },
    {
        "bbox": [
            384,
            247,
            405,
            262
        ],
        "class": 0,
        "iou": 0
    },
    {
        "bbox": [
            0,
            16,
            144,
            20
        ],
        "class": 0,
        "iou": 0
    },
    {
        "bbox": [
            0,
            7,
            534,
            293
        ],
        "class": 0,
        "iou": 0.25339828710615225
    },
    {
        "bbox": [
            271,
            150,
            298,
            174
        ],
        "class": 0,
        "iou": 0.01674418604651163
    },
    {
        "bbox": [
            128,
            108,
            213,
            149
        ],
        "class": 0,
        "iou": 0.0712290502793296
    },
    {
        "bbox": [
            285,
            224,
            329,
            259
        ],
        "class": 0,
        "iou": 0.013219186705275086
    },
    {
        "bbox": [
            327,
            7,
            411,
            16
        ],
        "class": 0,
        "iou": 0
    },
    {
        "bbox": [
            65,
            109,
            213,
            159
        ],
        "class": 0,
        "iou": 0.16015703644050736
    },
    {
        "bbox": [
            515,
            284,
            534,
            300
        ],
        "class": 0,
        "iou": 0
    },
    {
        "bbox": [
            157,
            161,
            201,
            169
        ],
        "class": 0,
        "iou": 0.00909560723514212
    },
    {
        "bbox": [
            383,
            260,
            405,
            267
        ],
        "class": 0,
        "iou": 0
    },
    {
        "bbox": [
            425,
            241,
            433,
            260
        ],
        "class": 0,
        "iou": 0
    },
    {
        "bbox": [
            418,
            255,
            433,
            267
        ],
        "class": 0,
        "iou": 0
    },
    {
        "bbox": [
            359,
            215,
            377,
            231
        ],
        "class": 0,
        "iou": 0
    },
    {
        "bbox": [
            0,
            32,
            6,
            64
        ],
        "class": 0,
        "iou": 0
    },
    {
        "bbox": [
            221,
            0,
            281,
            17
        ],
        "class": 0,
        "iou": 0
    },
    {
        "bbox": [
            399,
            233,
            447,
            290
        ],
        "class": 0,
        "iou": 0
    },
    {
        "bbox": [
            60,
            119,
            117,
            129
        ],
        "class": 0,
        "iou": 0.014728682170542635
    },
    {
        "bbox": [
            133,
            7,
            208,
            16
        ],
        "class": 0,
        "iou": 0
    },
    {
        "bbox": [
            465,
            0,
            520,
            8
        ],
        "class": 0,
        "iou": 0
    },
    {
        "bbox": [
            0,
            17,
            160,
            33
        ],
        "class": 0,
        "iou": 0
    },
    {
        "bbox": [
            407,
            240,
            415,
            267
        ],
        "class": 0,
        "iou": 0
    },
    {
        "bbox": [
            240,
            0,
            495,
            16
        ],
        "class": 0,
        "iou": 0
    },
    {
        "bbox": [
            106,
            128,
            118,
            144
        ],
        "class": 0,
        "iou": 0.00496124031007752
    },
    {
        "bbox": [
            256,
            80,
            288,
            96
        ],
        "class": 0,
        "iou": 0
    },
    {
        "bbox": [
            76,
            265,
            235,
            300
        ],
        "class": 0,
        "iou": 0.003604951707250714
    },
    {
        "bbox": [
            380,
            254,
            405,
            267
        ],
        "class": 0,
        "iou": 0
    },
    {
        "bbox": [
            348,
            233,
            417,
            300
        ],
        "class": 0,
        "iou": 0
    },
    {
        "bbox": [
            386,
            241,
            407,
            266
        ],
        "class": 0,
        "iou": 0
    },
    {
        "bbox": [
            0,
            118,
            519,
            300
        ],
        "class": null,
        "iou": 0.40204687598711225
    },
    {
        "bbox": [
            383,
            241,
            411,
            281
        ],
        "class": 0,
        "iou": 0
    },
    {
        "bbox": [
            232,
            222,
            252,
            245
        ],
        "class": 0,
        "iou": 0.011886304909560724
    },
    {
        "bbox": [
            257,
            81,
            287,
            95
        ],
        "class": 0,
        "iou": 0
    },
    {
        "bbox": [
            320,
            65,
            351,
            95
        ],
        "class": 0,
        "iou": 0
    },
    {
        "bbox": [
            407,
            240,
            415,
            266
        ],
        "class": 0,
        "iou": 0
    },
    {
        "bbox": [
            90,
            264,
            128,
            281
        ],
        "class": 0,
        "iou": 0.001935319582378406
    },
    {
        "bbox": [
            65,
            118,
            136,
            135
        ],
        "class": 0,
        "iou": 0.031188630490956073
    },
    {
        "bbox": [
            232,
            227,
            245,
            236
        ],
        "class": 0,
        "iou": 0.0030232558139534882
    },
    {
        "bbox": [
            252,
            7,
            281,
            17
        ],
        "class": 0,
        "iou": 0
    },
    {
        "bbox": [
            0,
            9,
            534,
            146
        ],
        "class": 0,
        "iou": 0.07433873105514896
    },
    {
        "bbox": [
            348,
            233,
            447,
            300
        ],
        "class": 0,
        "iou": 0
    },
    {
        "bbox": [
            370,
            239,
            397,
            266
        ],
        "class": 0,
        "iou": 0
    },
    {
        "bbox": [
            0,
            5,
            534,
            293
        ],
        "class": 0,
        "iou": 0.25163857677902624
    },
    {
        "bbox": [
            46,
            275,
            71,
            292
        ],
        "class": 0,
        "iou": 0
    },
    {
        "bbox": [
            383,
            247,
            405,
            267
        ],
        "class": 0,
        "iou": 0
    },
    {
        "bbox": [
            276,
            186,
            315,
            227
        ],
        "class": 0,
        "iou": 0.02502861503243037
    },
    {
        "bbox": [
            292,
            7,
            368,
            18
        ],
        "class": 0,
        "iou": 0
    },
    {
        "bbox": [
            221,
            0,
            261,
            14
        ],
        "class": 0,
        "iou": 0
    },
    {
        "bbox": [
            162,
            205,
            179,
            221
        ],
        "class": 0,
        "iou": 0.007028423772609819
    },
    {
        "bbox": [
            178,
            175,
            230,
            215
        ],
        "class": 0,
        "iou": 0.053746770025839795
    },
    {
        "bbox": [
            224,
            0,
            495,
            16
        ],
        "class": 0,
        "iou": 0
    },
    {
        "bbox": [
            383,
            261,
            421,
            281
        ],
        "class": 0,
        "iou": 0
    },
    {
        "bbox": [
            292,
            7,
            327,
            16
        ],
        "class": 0,
        "iou": 0
    },
    {
        "bbox": [
            276,
            186,
            315,
            221
        ],
        "class": 0,
        "iou": 0.02141491395793499
    },
    {
        "bbox": [
            0,
            104,
            301,
            284
        ],
        "class": 1,
        "iou": 0.7142857142857143
    },
    {
        "bbox": [
            279,
            183,
            302,
            208
        ],
        "class": 0,
        "iou": 0.013548387096774193
    },
    {
        "bbox": [
            127,
            138,
            157,
            159
        ],
        "class": 0,
        "iou": 0.01627906976744186
    },
    {
        "bbox": [
            119,
            201,
            301,
            274
        ],
        "class": 0,
        "iou": 0.2925088883916362
    },
    {
        "bbox": [
            220,
            201,
            301,
            274
        ],
        "class": 0,
        "iou": 0.13193616319488494
    },
    {
        "bbox": [
            270,
            154,
            310,
            191
        ],
        "class": 0,
        "iou": 0.028410545175326336
    },
    {
        "bbox": [
            119,
            279,
            160,
            289
        ],
        "class": 0,
        "iou": 0
    },
    {
        "bbox": [
            426,
            241,
            433,
            260
        ],
        "class": 0,
        "iou": 0
    },
    {
        "bbox": [
            429,
            238,
            448,
            279
        ],
        "class": 0,
        "iou": 0
    },
    {
        "bbox": [
            225,
            138,
            272,
            149
        ],
        "class": 0,
        "iou": 0.013359173126614988
    },
    {
        "bbox": [
            7,
            32,
            16,
            64
        ],
        "class": 0,
        "iou": 0
    },
    {
        "bbox": [
            102,
            9,
            193,
            17
        ],
        "class": 0,
        "iou": 0
    },
    {
        "bbox": [
            219,
            13,
            256,
            24
        ],
        "class": 0,
        "iou": 0
    },
    {
        "bbox": [
            270,
            154,
            311,
            224
        ],
        "class": 0,
        "iou": 0.0532049657968077
    },
    {
        "bbox": [
            159,
            0,
            240,
            16
        ],
        "class": 0,
        "iou": 0
    },
    {
        "bbox": [
            417,
            235,
            448,
            283
        ],
        "class": 0,
        "iou": 0
    },
    {
        "bbox": [
            425,
            240,
            433,
            260
        ],
        "class": 0,
        "iou": 0
    },
    {
        "bbox": [
            404,
            234,
            415,
            263
        ],
        "class": 0,
        "iou": 0
    },
    {
        "bbox": [
            237,
            114,
            335,
            132
        ],
        "class": 0,
        "iou": 0.025547445255474453
    },
    {
        "bbox": [
            243,
            137,
            310,
            189
        ],
        "class": 0,
        "iou": 0.0755736868944416
    },
    {
        "bbox": [
            60,
            119,
            117,
            136
        ],
        "class": 0,
        "iou": 0.02503875968992248
    },
    {
        "bbox": [
            306,
            235,
            340,
            261
        ],
        "class": 0,
        "iou": 0
    },
    {
        "bbox": [
            345,
            232,
            433,
            300
        ],
        "class": 0,
        "iou": 0
    },
    {
        "bbox": [
            351,
            233,
            385,
            263
        ],
        "class": 0,
        "iou": 0
    },
    {
        "bbox": [
            327,
            7,
            411,
            17
        ],
        "class": 0,
        "iou": 0
    },
    {
        "bbox": [
            224,
            6,
            262,
            14
        ],
        "class": 0,
        "iou": 0
    },
    {
        "bbox": [
            345,
            233,
            411,
            300
        ],
        "class": 0,
        "iou": 0
    },
    {
        "bbox": [
            406,
            240,
            415,
            266
        ],
        "class": 0,
        "iou": 0
    },
    {
        "bbox": [
            0,
            109,
            511,
            300
        ],
        "class": null,
        "iou": 0.3965123308162826
    },
    {
        "bbox": [
            463,
            0,
            520,
            8
        ],
        "class": 0,
        "iou": 0
    },
    {
        "bbox": [
            441,
            110,
            461,
            134
        ],
        "class": 0,
        "iou": 0
    },
    {
        "bbox": [
            253,
            138,
            281,
            155
        ],
        "class": 0,
        "iou": 0.012299741602067184
    },
    {
        "bbox": [
            167,
            205,
            177,
            221
        ],
        "class": 0,
        "iou": 0.004134366925064599
    },
    {
        "bbox": [
            370,
            239,
            396,
            266
        ],
        "class": 0,
        "iou": 0
    },
    {
        "bbox": [
            340,
            0,
            534,
            8
        ],
        "class": 0,
        "iou": 0
    },
    {
        "bbox": [
            5,
            272,
            45,
            282
        ],
        "class": 0,
        "iou": 0
    },
    {
        "bbox": [
            418,
            235,
            442,
            266
        ],
        "class": 0,
        "iou": 0
    },
    {
        "bbox": [
            292,
            0,
            534,
            33
        ],
        "class": 0,
        "iou": 0
    },
    {
        "bbox": [
            285,
            221,
            340,
            261
        ],
        "class": 0,
        "iou": 0.01488833746898263
    },
    {
        "bbox": [
            159,
            0,
            222,
            16
        ],
        "class": 0,
        "iou": 0
    },
    {
        "bbox": [
            348,
            245,
            417,
            300
        ],
        "class": 0,
        "iou": 0
    },
    {
        "bbox": [
            67,
            109,
            159,
            123
        ],
        "class": 0,
        "iou": 0.016368442456283043
    },
    {
        "bbox": [
            0,
            104,
            315,
            284
        ],
        "class": 1,
        "iou": 0.6825396825396826
    },
    {
        "bbox": [
            0,
            0,
            479,
            24
        ],
        "class": 0,
        "iou": 0
    },
    {
        "bbox": [
            202,
            211,
            297,
            270
        ],
        "class": 0,
        "iou": 0.13370010235414534
    },
    {
        "bbox": [
            122,
            282,
            160,
            289
        ],
        "class": 0,
        "iou": 0
    },
    {
        "bbox": [
            203,
            237,
            237,
            256
        ],
        "class": 0,
        "iou": 0.016692506459948322
    },
    {
        "bbox": [
            0,
            0,
            534,
            19
        ],
        "class": 0,
        "iou": 0
    },
    {
        "bbox": [
            0,
            20,
            32,
            33
        ],
        "class": 0,
        "iou": 0
    },
    {
        "bbox": [
            405,
            235,
            415,
            267
        ],
        "class": 0,
        "iou": 0
    },
    {
        "bbox": [
            150,
            137,
            200,
            162
        ],
        "class": 0,
        "iou": 0.03229974160206718
    },
    {
        "bbox": [
            419,
            267,
            440,
            280
        ],
        "class": 0,
        "iou": 0
    },
    {
        "bbox": [
            432,
            0,
            534,
            33
        ],
        "class": 0,
        "iou": 0
    },
    {
        "bbox": [
            73,
            109,
            213,
            161
        ],
        "class": 0,
        "iou": 0.1587701612903226
    },
    {
        "bbox": [
            0,
            14,
            80,
            17
        ],
        "class": 0,
        "iou": 0
    },
    {
        "bbox": [
            421,
            269,
            440,
            283
        ],
        "class": 0,
        "iou": 0
    },
    {
        "bbox": [
            463,
            0,
            534,
            10
        ],
        "class": 0,
        "iou": 0
    },
    {
        "bbox": [
            65,
            108,
            213,
            149
        ],
        "class": 0,
        "iou": 0.12245511984755791
    },
    {
        "bbox": [
            345,
            233,
            433,
            300
        ],
        "class": 0,
        "iou": 0
    },
    {
        "bbox": [
            268,
            155,
            315,
            221
        ],
        "class": 0,
        "iou": 0.053212396069538925
    },
    {
        "bbox": [
            293,
            204,
            309,
            228
        ],
        "class": 0,
        "iou": 0.004316990440949738
    },
    {
        "bbox": [
            381,
            232,
            406,
            257
        ],
        "class": 0,
        "iou": 0
    },
    {
        "bbox": [
            0,
            270,
            108,
            300
        ],
        "class": 0,
        "iou": 0
    },
    {
        "bbox": [
            160,
            237,
            235,
            268
        ],
        "class": 0,
        "iou": 0.055984555984555984
    },
    {
        "bbox": [
            448,
            32,
            464,
            48
        ],
        "class": 0,
        "iou": 0
    },
    {
        "bbox": [
            0,
            104,
            329,
            300
        ],
        "class": 1,
        "iou": 0.6001488741393214
    },
    {
        "bbox": [
            405,
            236,
            414,
            266
        ],
        "class": 0,
        "iou": 0
    },
    {
        "bbox": [
            119,
            201,
            340,
            274
        ],
        "class": 0,
        "iou": 0.27317265719327577
    },
    {
        "bbox": [
            0,
            111,
            301,
            300
        ],
        "class": 1,
        "iou": 0.6802721088435374
    },
    {
        "bbox": [
            292,
            5,
            496,
            24
        ],
        "class": 0,
        "iou": 0
    },
    {
        "bbox": [
            0,
            109,
            340,
            300
        ],
        "class": 1,
        "iou": 0.5959347089621189
    },
    {
        "bbox": [
            180,
            181,
            223,
            221
        ],
        "class": 0,
        "iou": 0.044444444444444446
    },
    {
        "bbox": [
            202,
            222,
            252,
            268
        ],
        "class": 0,
        "iou": 0.05670103092783505
    },
    {
        "bbox": [
            243,
            137,
            282,
            155
        ],
        "class": 0,
        "iou": 0.01813953488372093
    },
    {
        "bbox": [
            102,
            9,
            193,
            16
        ],
        "class": 0,
        "iou": 0
    },
    {
        "bbox": [
            278,
            183,
            304,
            208
        ],
        "class": 0,
        "iou": 0.014175257731958763
    },
    {
        "bbox": [
            200,
            216,
            329,
            277
        ],
        "class": 0,
        "iou": 0.12028194086939786
    },
    {
        "bbox": [
            47,
            183,
            73,
            209
        ],
        "class": 0,
        "iou": 0.017467700258397934
    },
    {
        "bbox": [
            147,
            115,
            215,
            160
        ],
        "class": 0,
        "iou": 0.0771770532397854
    },
    {
        "bbox": [
            134,
            200,
            179,
            220
        ],
        "class": 0,
        "iou": 0.023255813953488372
    },
    {
        "bbox": [
            204,
            237,
            238,
            265
        ],
        "class": 0,
        "iou": 0.024599483204134368
    },
    {
        "bbox": [
            119,
            238,
            161,
            258
        ],
        "class": 0,
        "iou": 0.021705426356589147
    },
    {
        "bbox": [
            0,
            33,
            6,
            64
        ],
        "class": 0,
        "iou": 0
    },
    {
        "bbox": [
            386,
            259,
            433,
            300
        ],
        "class": 0,
        "iou": 0
    },
    {
        "bbox": [
            0,
            5,
            534,
            300
        ],
        "class": 0,
        "iou": 0.24566749190630355
    },
    {
        "bbox": [
            223,
            7,
            261,
            14
        ],
        "class": 0,
        "iou": 0
    },
    {
        "bbox": [
            262,
            99,
            324,
            132
        ],
        "class": 0,
        "iou": 0.015147740295978873
    },
    {
        "bbox": [
            400,
            214,
            447,
            266
        ],
        "class": 0,
        "iou": 0
    },
    {
        "bbox": [
            102,
            7,
            208,
            17
        ],
        "class": 0,
        "iou": 0
    },
    {
        "bbox": [
            250,
            0,
            396,
            16
        ],
        "class": 0,
        "iou": 0
    },
    {
        "bbox": [
            46,
            275,
            76,
            292
        ],
        "class": 0,
        "iou": 0
    },
    {
        "bbox": [
            255,
            79,
            289,
            97
        ],
        "class": 0,
        "iou": 0
    },
    {
        "bbox": [
            404,
            234,
            423,
            263
        ],
        "class": 0,
        "iou": 0
    },
    {
        "bbox": [
            0,
            0,
            205,
            18
        ],
        "class": 0,
        "iou": 0
    },
    {
        "bbox": [
            144,
            138,
            200,
            164
        ],
        "class": 0,
        "iou": 0.03762273901808785
    },
    {
        "bbox": [
            416,
            20,
            480,
            24
        ],
        "class": 0,
        "iou": 0
    },
    {
        "bbox": [
            422,
            264,
            439,
            283
        ],
        "class": 0,
        "iou": 0
    },
    {
        "bbox": [
            124,
            138,
            164,
            159
        ],
        "class": 0,
        "iou": 0.021705426356589147
    },
    {
        "bbox": [
            433,
            104,
            450,
            113
        ],
        "class": 0,
        "iou": 0
    },
    {
        "bbox": [
            90,
            265,
            131,
            281
        ],
        "class": 0,
        "iou": 0.0010428589596845987
    },
    {
        "bbox": [
            200,
            48,
            208,
            63
        ],
        "class": 0,
        "iou": 0
    },
    {
        "bbox": [
            167,
            205,
            179,
            221
        ],
        "class": 0,
        "iou": 0.00496124031007752
    },
    {
        "bbox": [
            160,
            0,
            224,
            15
        ],
        "class": 0,
        "iou": 0
    },
    {
        "bbox": [
            335,
            0,
            408,
            5
        ],
        "class": 0,
        "iou": 0
    },
    {
        "bbox": [
            0,
            0,
            256,
            18
        ],
        "class": 0,
        "iou": 0
    },
    {
        "bbox": [
            250,
            0,
            340,
            16
        ],
        "class": 0,
        "iou": 0
    },
    {
        "bbox": [
            124,
            138,
            200,
            164
        ],
        "class": 0,
        "iou": 0.0510594315245478
    },
    {
        "bbox": [
            383,
            234,
            442,
            281
        ],
        "class": 0,
        "iou": 0
    },
    {
        "bbox": [
            0,
            0,
            534,
            17
        ],
        "class": 0,
        "iou": 0
    },
    {
        "bbox": [
            397,
            234,
            423,
            266
        ],
        "class": 0,
        "iou": 0
    },
    {
        "bbox": [
            326,
            12,
            368,
            18
        ],
        "class": 0,
        "iou": 0
    },
    {
        "bbox": [
            207,
            93,
            534,
            300
        ],
        "class": 0,
        "iou": 0.15091033005549606
    },
    {
        "bbox": [
            127,
            115,
            215,
            160
        ],
        "class": 0,
        "iou": 0.09982468804784984
    },
    {
        "bbox": [
            0,
            280,
            36,
            300
        ],
        "class": 0,
        "iou": 0
    },
    {
        "bbox": [
            345,
            214,
            447,
            300
        ],
        "class": 0,
        "iou": 0
    },
    {
        "bbox": [
            200,
            216,
            301,
            277
        ],
        "class": 0,
        "iou": 0.12543588971676575
    },
    {
        "bbox": [
            208,
            270,
            234,
            279
        ],
        "class": 0,
        "iou": 0
    },
    {
        "bbox": [
            0,
            118,
            534,
            300
        ],
        "class": null,
        "iou": 0.3908130680422501
    },
    {
        "bbox": [
            0,
            122,
            35,
            132
        ],
        "class": 0,
        "iou": 0
    },
    {
        "bbox": [
            417,
            234,
            438,
            267
        ],
        "class": 0,
        "iou": 0
    },
    {
        "bbox": [
            370,
            234,
            443,
            281
        ],
        "class": 0,
        "iou": 0
    },
    {
        "bbox": [
            451,
            289,
            464,
            300
        ],
        "class": 0,
        "iou": 0
    },
    {
        "bbox": [
            60,
            109,
            159,
            136
        ],
        "class": 0,
        "iou": 0.05026273703449852
    },
    {
        "bbox": [
            467,
            107,
            480,
            126
        ],
        "class": 0,
        "iou": 0
    },
    {
        "bbox": [
            124,
            137,
            200,
            162
        ],
        "class": 0,
        "iou": 0.04909560723514212
    },
    {
        "bbox": [
            424,
            239,
            433,
            262
        ],
        "class": 0,
        "iou": 0
    },
    {
        "bbox": [
            226,
            0,
            253,
            6
        ],
        "class": 0,
        "iou": 0
    },
    {
        "bbox": [
            47,
            182,
            73,
            205
        ],
        "class": 0,
        "iou": 0.01545219638242894
    },
    {
        "bbox": [
            235,
            99,
            324,
            132
        ],
        "class": 0,
        "iou": 0.025617656477079587
    },
    {
        "bbox": [
            0,
            252,
            44,
            300
        ],
        "class": 0,
        "iou": 0.0006865437426441742
    },
    {
        "bbox": [
            119,
            234,
            235,
            268
        ],
        "class": 0,
        "iou": 0.09534573101818555
    },
    {
        "bbox": [
            67,
            109,
            264,
            149
        ],
        "class": 0,
        "iou": 0.16220464582449662
    },
    {
        "bbox": [
            0,
            0,
            479,
            33
        ],
        "class": 0,
        "iou": 0
    },
    {
        "bbox": [
            0,
            0,
            224,
            19
        ],
        "class": 0,
        "iou": 0
    },
    {
        "bbox": [
            65,
            108,
            213,
            162
        ],
        "class": 0,
        "iou": 0.17069501554508074
    },
    {
        "bbox": [
            0,
            0,
            222,
            19
        ],
        "class": 0,
        "iou": 0
    },
    {
        "bbox": [
            202,
            222,
            265,
            268
        ],
        "class": 0,
        "iou": 0.07139545665275845
    },
    {
        "bbox": [
            0,
            265,
            131,
            300
        ],
        "class": 0,
        "iou": 0.0020603759607371055
    },
    {
        "bbox": [
            383,
            234,
            461,
            281
        ],
        "class": 0,
        "iou": 0
    },
    {
        "bbox": [
            253,
            138,
            310,
            191
        ],
        "class": 0,
        "iou": 0.06349732347693092
    },
    {
        "bbox": [
            422,
            238,
            448,
            283
        ],
        "class": 0,
        "iou": 0
    },
    {
        "bbox": [
            129,
            7,
            208,
            16
        ],
        "class": 0,
        "iou": 0
    },
    {
        "bbox": [
            383,
            233,
            447,
            290
        ],
        "class": 0,
        "iou": 0
    },
    {
        "bbox": [
            216,
            0,
            495,
            17
        ],
        "class": 0,
        "iou": 0
    },
    {
        "bbox": [
            0,
            155,
            329,
            300
        ],
        "class": null,
        "iou": 0.49575016878148426
    },
    {
        "bbox": [
            343,
            0,
            534,
            8
        ],
        "class": 0,
        "iou": 0
    },
    {
        "bbox": [
            253,
            138,
            315,
            221
        ],
        "class": 0,
        "iou": 0.0976592815120791
    },
    {
        "bbox": [
            370,
            234,
            461,
            281
        ],
        "class": 0,
        "iou": 0
    },
    {
        "bbox": [
            345,
            214,
            448,
            300
        ],
        "class": 0,
        "iou": 0
    },
    {
        "bbox": [
            0,
            0,
            534,
            145
        ],
        "class": 0,
        "iou": 0.06886459023635962
    },
    {
        "bbox": [
            278,
            183,
            310,
            228
        ],
        "class": 0,
        "iou": 0.02528735632183908
    },
    {
        "bbox": [
            219,
            6,
            262,
            24
        ],
        "class": 0,
        "iou": 0
    },
    {
        "bbox": [
            124,
            112,
            264,
            164
        ],
        "class": 0,
        "iou": 0.17116658176260827
    },
    {
        "bbox": [
            0,
            265,
            234,
            300
        ],
        "class": 0,
        "iou": 0.004111525118848773
    },
    {
        "bbox": [
            279,
            183,
            309,
            228
        ],
        "class": 0,
        "iou": 0.024165707710011506
    },
    {
        "bbox": [
            512,
            16,
            534,
            79
        ],
        "class": 0,
        "iou": 0
    },
    {
        "bbox": [
            243,
            137,
            315,
            227
        ],
        "class": 0,
        "iou": 0.12808988764044943
    },
    {
        "bbox": [
            380,
            233,
            447,
            283
        ],
        "class": 0,
        "iou": 0
    },
    {
        "bbox": [
            0,
            0,
            240,
            18
        ],
        "class": 0,
        "iou": 0
    },
    {
        "bbox": [
            417,
            235,
            448,
            279
        ],
        "class": 0,
        "iou": 0
    },
    {
        "bbox": [
            60,
            109,
            264,
            149
        ],
        "class": 0,
        "iou": 0.16776315789473684
    },
    {
        "bbox": [
            0,
            0,
            534,
            33
        ],
        "class": 0,
        "iou": 0
    },
    {
        "bbox": [
            370,
            239,
            411,
            281
        ],
        "class": 0,
        "iou": 0
    },
    {
        "bbox": [
            404,
            234,
            461,
            279
        ],
        "class": 0,
        "iou": 0
    },
    {
        "bbox": [
            220,
            201,
            340,
            274
        ],
        "class": 0,
        "iou": 0.12304779933743493
    },
    {
        "bbox": [
            397,
            234,
            442,
            272
        ],
        "class": 0,
        "iou": 0
    },
    {
        "bbox": [
            404,
            234,
            443,
            267
        ],
        "class": 0,
        "iou": 0
    },
    {
        "bbox": [
            0,
            0,
            281,
            19
        ],
        "class": 0,
        "iou": 0
    },
    {
        "bbox": [
            0,
            0,
            261,
            19
        ],
        "class": 0,
        "iou": 0
    },
    {
        "bbox": [
            268,
            155,
            315,
            227
        ],
        "class": 0,
        "iou": 0.0579185520361991
    },
    {
        "bbox": [
            0,
            16,
            160,
            32
        ],
        "class": 0,
        "iou": 0
    },
    {
        "bbox": [
            65,
            92,
            213,
            162
        ],
        "class": 0,
        "iou": 0.16112846729148916
    },
    {
        "bbox": [
            60,
            109,
            340,
            274
        ],
        "class": 1,
        "iou": 0.7361963190184049
    },
    {
        "bbox": [
            381,
            232,
            415,
            263
        ],
        "class": 0,
        "iou": 0
    },
    {
        "bbox": [
            0,
            7,
            534,
            300
        ],
        "class": 0,
        "iou": 0.2473444031138551
    },
    {
        "bbox": [
            419,
            241,
            461,
            281
        ],
        "class": 0,
        "iou": 0
    },
    {
        "bbox": [
            326,
            5,
            496,
            24
        ],
        "class": 0,
        "iou": 0
    },
    {
        "bbox": [
            124,
            112,
            315,
            221
        ],
        "class": null,
        "iou": 0.4503033699651551
    },
    {
        "bbox": [
            0,
            109,
            519,
            300
        ],
        "class": null,
        "iou": 0.39040038737402777
    },
    {
        "bbox": [
            250,
            0,
            479,
            16
        ],
        "class": 0,
        "iou": 0
    },
    {
        "bbox": [
            383,
            234,
            423,
            281
        ],
        "class": 0,
        "iou": 0
    },
    {
        "bbox": [
            200,
            155,
            329,
            277
        ],
        "class": 0,
        "iou": 0.25612626332548805
    },
    {
        "bbox": [
            0,
            16,
            160,
            33
        ],
        "class": 0,
        "iou": 0
    },
    {
        "bbox": [
            292,
            0,
            534,
            79
        ],
        "class": 0,
        "iou": 0
    },
    {
        "bbox": [
            60,
            109,
            315,
            221
        ],
        "class": 1,
        "iou": 0.5991440798858774
    },
    {
        "bbox": [
            0,
            7,
            208,
            33
        ],
        "class": 0,
        "iou": 0
    },
    {
        "bbox": [
            404,
            234,
            438,
            267
        ],
        "class": 0,
        "iou": 0
    },
    {
        "bbox": [
            0,
            270,
            234,
            300
        ],
        "class": 0,
        "iou": 0
    },
    {
        "bbox": [
            397,
            234,
            461,
            279
        ],
        "class": 0,
        "iou": 0
    },
    {
        "bbox": [
            0,
            0,
            520,
            33
        ],
        "class": 0,
        "iou": 0
    },
    {
        "bbox": [
            0,
            9,
            193,
            33
        ],
        "class": 0,
        "iou": 0
    },
    {
        "bbox": [
            60,
            109,
            264,
            164
        ],
        "class": 0,
        "iou": 0.24401913875598086
    },
    {
        "bbox": [
            0,
            0,
            534,
            146
        ],
        "class": 0,
        "iou": 0.07105871984135728
    },
    {
        "bbox": [
            60,
            109,
            340,
            261
        ],
        "class": 1,
        "iou": 0.7490314248816186
    },
    {
        "bbox": [
            397,
            234,
            461,
            280
        ],
        "class": 0,
        "iou": 0
    },
    {
        "bbox": [
            0,
            97,
            534,
            300
        ],
        "class": null,
        "iou": 0.35700448331211604
    },
    {
        "bbox": [
            0,
            216,
            329,
            300
        ],
        "class": 0,
        "iou": 0.2414102852009881
    },
    {
        "bbox": [
            370,
            234,
            442,
            281
        ],
        "class": 0,
        "iou": 0
    },
    {
        "bbox": [
            0,
            92,
            301,
            284
        ],
        "class": 1,
        "iou": 0.6696428571428571
    },
    {
        "bbox": [
            404,
            234,
            461,
            281
        ],
        "class": 0,
        "iou": 0
    },
    {
        "bbox": [
            0,
            92,
            329,
            300
        ],
        "class": 1,
        "iou": 0.5655249006312836
    },
    {
        "bbox": [
            0,
            0,
            534,
            79
        ],
        "class": 0,
        "iou": 0
    },
    {
        "bbox": [
            0,
            92,
            534,
            300
        ],
        "class": null,
        "iou": 0.34842264477095936
    },
    {
        "bbox": [
            0,
            93,
            534,
            300
        ],
        "class": null,
        "iou": 0.3501058459534278
    }
]